EriduLab_tool/__init__.py
EriduLab_tool/labs/MCD.py
EriduLab_tool/labs/__init__.py
eridulab_tool-0.0.7.dist-info/licenses/LICENSE
eridulab_tool-0.0.7.dist-info/METADATA
eridulab_tool-0.0.7.dist-info/WHEEL
eridulab_tool-0.0.7.dist-info/top_level.txt
eridulab_tool-0.0.7.dist-info/RECORD
